surquest/utils/requirements.txt
surquest/utils/appstoreconnect/credentials.py
surquest/utils/appstoreconnect/init.py
surquest/utils/appstoreconnect/analyticsreports/client.py
surquest/utils/appstoreconnect/analyticsreports/errors.py
surquest/utils/appstoreconnect/analyticsreports/handler.py
surquest/utils/appstoreconnect/analyticsreports/init.py
surquest/utils/appstoreconnect/analyticsreports/logger.py
surquest/utils/appstoreconnect/analyticsreports/enums/category.py
surquest/utils/appstoreconnect/analyticsreports/enums/granularity.py
surquest/utils/appstoreconnect/analyticsreports/enums/report_name.py
surquest_appstoreconnect_analyticsreports-0.0.1rc1.dist-info/METADATA
surquest_appstoreconnect_analyticsreports-0.0.1rc1.dist-info/WHEEL
surquest_appstoreconnect_analyticsreports-0.0.1rc1.dist-info/licenses/LICENSE
surquest_appstoreconnect_analyticsreports-0.0.1rc1.dist-info/RECORD
